{"dependencies":[{"name":"E:\\htdocs\\tao-carousel\\package.json","includedInParent":true,"mtime":1523967658758},{"name":"E:\\htdocs\\tao-carousel\\.babelrc","includedInParent":true,"mtime":1523967535799},{"name":"E:\\htdocs\\tao-carousel\\node_modules\\babel-runtime\\package.json","includedInParent":true,"mtime":1502898848000},{"name":"core-js/library/fn/object/assign","loc":{"line":1,"column":38}}],"generated":{"js":"module.exports = { \"default\": require(\"core-js/library/fn/object/assign\"), __esModule: true };","map":{"mappings":[{"source":"node_modules\\babel-runtime\\core-js\\object\\assign.js","original":{"line":1,"column":0},"generated":{"line":1,"column":0}}],"sources":{"node_modules\\babel-runtime\\core-js\\object\\assign.js":"module.exports = { \"default\": require(\"core-js/library/fn/object/assign\"), __esModule: true };"},"lineCount":1}},"hash":"b9222537425116a4a699844ef1bd2e7d","cacheData":{"env":{}}}