{"dependencies":[{"name":"E:\\htdocs\\tao-carousel\\.babelrc","includedInParent":true,"mtime":1523967535799},{"name":"E:\\htdocs\\tao-carousel\\package.json","includedInParent":true,"mtime":1523967658758},{"name":"./lib/tao-carousel","loc":{"line":1,"column":24}}],"generated":{"js":"'use strict';\n\nvar _taoCarousel = require('./lib/tao-carousel');\n\nvar _taoCarousel2 = _interopRequireDefault(_taoCarousel);\n\nfunction _interopRequireDefault(obj) { return obj && obj.__esModule ? obj : { default: obj }; }\n\nvar config = {\n    // activeClass: 'active',\n    // carouselBox: '.carousel-box',\n    // carouselContent: '.carousel-content',\n    // carouselItem: '.carousel-item',\n};\nvar $el = document.querySelector('.carousel');\nvar carousel = new _taoCarousel2.default($el, config);\n// setTimeout(() => {\n//     carousel.destroy();\n// }, 5000);\n// taoCarousel.create($el, config);","map":{"mappings":[{"generated":{"line":3,"column":0},"source":"index.js","original":{"line":1,"column":0}},{"generated":{"line":9,"column":0},"source":"index.js","original":{"line":3,"column":0}},{"name":"config","generated":{"line":9,"column":4},"source":"index.js","original":{"line":3,"column":6}},{"generated":{"line":9,"column":13},"source":"index.js","original":{"line":3,"column":15}},{"generated":{"line":10,"column":0},"source":"index.js","original":{"line":4,"column":4}},{"generated":{"line":11,"column":0},"source":"index.js","original":{"line":5,"column":4}},{"generated":{"line":12,"column":0},"source":"index.js","original":{"line":6,"column":4}},{"generated":{"line":13,"column":0},"source":"index.js","original":{"line":7,"column":4}},{"generated":{"line":14,"column":0},"source":"index.js","original":{"line":3,"column":15}},{"generated":{"line":14,"column":1},"source":"index.js","original":{"line":3,"column":0}},{"generated":{"line":15,"column":0},"source":"index.js","original":{"line":9,"column":0}},{"name":"$el","generated":{"line":15,"column":4},"source":"index.js","original":{"line":9,"column":6}},{"name":"document","generated":{"line":15,"column":10},"source":"index.js","original":{"line":9,"column":12}},{"name":"querySelector","generated":{"line":15,"column":19},"source":"index.js","original":{"line":9,"column":21}},{"generated":{"line":15,"column":32},"source":"index.js","original":{"line":9,"column":12}},{"generated":{"line":15,"column":33},"source":"index.js","original":{"line":9,"column":35}},{"generated":{"line":15,"column":44},"source":"index.js","original":{"line":9,"column":12}},{"generated":{"line":15,"column":45},"source":"index.js","original":{"line":9,"column":0}},{"generated":{"line":16,"column":0},"source":"index.js","original":{"line":10,"column":0}},{"name":"carousel","generated":{"line":16,"column":4},"source":"index.js","original":{"line":10,"column":6}},{"generated":{"line":16,"column":15},"source":"index.js","original":{"line":10,"column":17}},{"name":"$el","generated":{"line":16,"column":41},"source":"index.js","original":{"line":10,"column":33}},{"generated":{"line":16,"column":44},"source":"index.js","original":{"line":10,"column":17}},{"name":"config","generated":{"line":16,"column":46},"source":"index.js","original":{"line":10,"column":38}},{"generated":{"line":16,"column":52},"source":"index.js","original":{"line":10,"column":17}},{"generated":{"line":16,"column":53},"source":"index.js","original":{"line":10,"column":0}},{"generated":{"line":17,"column":0},"source":"index.js","original":{"line":11,"column":0}},{"generated":{"line":18,"column":0},"source":"index.js","original":{"line":12,"column":0}},{"generated":{"line":19,"column":0},"source":"index.js","original":{"line":13,"column":0}},{"generated":{"line":20,"column":0},"source":"index.js","original":{"line":14,"column":0}}],"sources":{"index.js":"import taoCarousel from './lib/tao-carousel';\r\n\r\nconst config = {\r\n    // activeClass: 'active',\r\n    // carouselBox: '.carousel-box',\r\n    // carouselContent: '.carousel-content',\r\n    // carouselItem: '.carousel-item',\r\n};\r\nconst $el = document.querySelector('.carousel');\r\nconst carousel = new taoCarousel($el, config);\r\n// setTimeout(() => {\r\n//     carousel.destroy();\r\n// }, 5000);\r\n// taoCarousel.create($el, config);"},"lineCount":null}},"hash":"5294e969324dcb57fc8d40fb5e8ec314","cacheData":{"env":{}}}